[{"title": null, "start": 1773283388, "stop": 1773288673}, {"title": null, "start": 1773288673, "stop": 1773294815}, {"title": null, "start": 1773294815, "stop": 1773300215}, {"title": null, "start": 1773300215, "stop": 1773305787}, {"title": null, "start": 1773305787, "stop": 1773311341}, {"title": null, "start": 1773311341, "stop": 1773316810}, {"title": null, "start": 1773316810, "stop": 1773322169}, {"title": null, "start": 1773322169, "stop": 1773327569}, {"title": null, "start": 1773327569, "stop": 1773334051}, {"title": null, "start": 1773334051, "stop": 1773339509}]