[{"title": "L'Ultimo Sharknado - Era Ora!", "start": 1772990052, "stop": 1772996232}, {"title": "Astronaut: the last push", "start": 1772996232, "stop": 1773001885}, {"title": "Galaxy Quest", "start": 1773001885, "stop": 1773008905}, {"title": "Alien Siege", "start": 1773008905, "stop": 1773014605}, {"title": "These final hours - 12 ore alla fine", "start": 1773014605, "stop": 1773020185}, {"title": "L'invasione degli ultra sbronzi", "start": 1773020185, "stop": 1773026125}, {"title": "Human Lost - Lo Squalificato", "start": 1773026125, "stop": 1773033265}, {"title": "After the dark", "start": 1773033265, "stop": 1773039965}, {"title": "Galaxy Quest", "start": 1773039965, "stop": 1773046985}]