[{"title": null, "start": 1773109137, "stop": 1773112789}, {"title": null, "start": 1773112789, "stop": 1773116343}, {"title": null, "start": 1773116343, "stop": 1773120013}, {"title": null, "start": 1773120013, "stop": 1773121513}, {"title": null, "start": 1773121513, "stop": 1773125173}, {"title": null, "start": 1773125173, "stop": 1773128833}, {"title": null, "start": 1773128833, "stop": 1773131833}, {"title": null, "start": 1773131833, "stop": 1773134833}, {"title": null, "start": 1773134833, "stop": 1773138013}, {"title": null, "start": 1773138013, "stop": 1773141193}, {"title": null, "start": 1773141193, "stop": 1773144433}, {"title": null, "start": 1773144433, "stop": 1773147493}, {"title": null, "start": 1773147493, "stop": 1773151033}, {"title": null, "start": 1773151033, "stop": 1773154573}, {"title": null, "start": 1773154573, "stop": 1773158113}, {"title": null, "start": 1773158113, "stop": 1773161653}, {"title": null, "start": 1773161653, "stop": 1773165313}]