[{"title": null, "start": 1773146829, "stop": 1773148389}, {"title": null, "start": 1773148389, "stop": 1773149949}, {"title": null, "start": 1773149949, "stop": 1773151509}, {"title": null, "start": 1773151509, "stop": 1773153069}, {"title": null, "start": 1773153069, "stop": 1773154629}, {"title": null, "start": 1773154629, "stop": 1773156189}, {"title": null, "start": 1773156189, "stop": 1773157749}, {"title": null, "start": 1773157749, "stop": 1773159309}, {"title": null, "start": 1773159309, "stop": 1773160869}, {"title": null, "start": 1773160869, "stop": 1773162429}, {"title": null, "start": 1773162429, "stop": 1773163989}, {"title": null, "start": 1773163989, "stop": 1773165549}, {"title": null, "start": 1773165549, "stop": 1773167182}, {"title": null, "start": 1773167182, "stop": 1773168815}, {"title": null, "start": 1773168815, "stop": 1773170448}, {"title": null, "start": 1773170448, "stop": 1773172081}, {"title": null, "start": 1773172081, "stop": 1773173714}, {"title": null, "start": 1773173714, "stop": 1773175347}, {"title": null, "start": 1773175347, "stop": 1773176847}, {"title": null, "start": 1773176847, "stop": 1773178347}, {"title": null, "start": 1773178347, "stop": 1773179847}, {"title": null, "start": 1773179847, "stop": 1773181347}, {"title": null, "start": 1773181347, "stop": 1773182847}, {"title": null, "start": 1773182847, "stop": 1773184347}, {"title": null, "start": 1773184347, "stop": 1773185847}, {"title": null, "start": 1773185847, "stop": 1773187347}, {"title": null, "start": 1773187347, "stop": 1773188847}, {"title": null, "start": 1773188847, "stop": 1773190347}, {"title": null, "start": 1773190347, "stop": 1773197007}, {"title": null, "start": 1773197007, "stop": 1773198507}, {"title": null, "start": 1773198507, "stop": 1773200067}, {"title": null, "start": 1773200067, "stop": 1773201627}]