[{"title": null, "start": 1773235920, "stop": 1773237720}, {"title": null, "start": 1773237720, "stop": 1773239520}, {"title": null, "start": 1773239520, "stop": 1773241320}, {"title": null, "start": 1773241320, "stop": 1773243120}, {"title": null, "start": 1773243120, "stop": 1773244920}, {"title": null, "start": 1773244920, "stop": 1773246720}, {"title": null, "start": 1773246720, "stop": 1773248520}, {"title": null, "start": 1773248520, "stop": 1773250320}, {"title": null, "start": 1773250320, "stop": 1773252120}, {"title": null, "start": 1773252120, "stop": 1773253920}, {"title": null, "start": 1773253920, "stop": 1773255720}, {"title": null, "start": 1773255720, "stop": 1773257520}, {"title": null, "start": 1773257520, "stop": 1773259320}, {"title": null, "start": 1773259320, "stop": 1773261120}, {"title": null, "start": 1773261120, "stop": 1773262920}, {"title": null, "start": 1773262920, "stop": 1773264720}, {"title": null, "start": 1773264720, "stop": 1773266520}, {"title": null, "start": 1773266520, "stop": 1773268320}, {"title": null, "start": 1773268320, "stop": 1773270120}, {"title": null, "start": 1773270120, "stop": 1773271920}, {"title": null, "start": 1773271920, "stop": 1773273720}, {"title": null, "start": 1773273720, "stop": 1773275520}, {"title": null, "start": 1773275520, "stop": 1773277320}, {"title": null, "start": 1773277320, "stop": 1773279120}, {"title": null, "start": 1773279120, "stop": 1773280920}, {"title": null, "start": 1773280920, "stop": 1773282720}, {"title": null, "start": 1773282720, "stop": 1773284520}, {"title": null, "start": 1773284520, "stop": 1773286320}, {"title": null, "start": 1773286320, "stop": 1773288120}]