[{"title": null, "start": 1773193464, "stop": 1773198800}, {"title": null, "start": 1773198800, "stop": 1773201553}, {"title": null, "start": 1773201553, "stop": 1773207118}, {"title": null, "start": 1773207118, "stop": 1773209963}, {"title": null, "start": 1773209963, "stop": 1773215184}, {"title": null, "start": 1773215184, "stop": 1773220692}, {"title": null, "start": 1773220692, "stop": 1773226197}, {"title": null, "start": 1773226197, "stop": 1773228995}, {"title": null, "start": 1773228995, "stop": 1773231820}, {"title": null, "start": 1773231820, "stop": 1773234605}, {"title": null, "start": 1773234605, "stop": 1773237465}, {"title": null, "start": 1773237465, "stop": 1773240266}, {"title": null, "start": 1773240266, "stop": 1773245896}]