[{"title": null, "start": 1773145750, "stop": 1773148800}, {"title": null, "start": 1773148800, "stop": 1773151850}, {"title": null, "start": 1773151850, "stop": 1773154900}, {"title": null, "start": 1773154900, "stop": 1773157950}, {"title": null, "start": 1773157950, "stop": 1773161000}, {"title": null, "start": 1773161000, "stop": 1773164050}, {"title": null, "start": 1773164050, "stop": 1773167100}, {"title": null, "start": 1773167100, "stop": 1773170150}, {"title": null, "start": 1773170150, "stop": 1773173200}, {"title": null, "start": 1773173200, "stop": 1773176250}, {"title": null, "start": 1773176250, "stop": 1773179300}, {"title": null, "start": 1773179300, "stop": 1773182350}, {"title": null, "start": 1773182350, "stop": 1773185400}, {"title": null, "start": 1773185400, "stop": 1773188450}, {"title": null, "start": 1773188450, "stop": 1773191500}, {"title": null, "start": 1773191500, "stop": 1773194550}, {"title": null, "start": 1773194550, "stop": 1773197600}, {"title": null, "start": 1773197600, "stop": 1773200650}, {"title": null, "start": 1773200650, "stop": 1773203700}]