[{"title": null, "start": 1773237060, "stop": 1773237600}, {"title": null, "start": 1773237600, "stop": 1773239400}, {"title": null, "start": 1773239400, "stop": 1773240000}, {"title": null, "start": 1773240000, "stop": 1773240360}, {"title": null, "start": 1773240360, "stop": 1773241200}, {"title": null, "start": 1773241200, "stop": 1773242100}, {"title": null, "start": 1773242100, "stop": 1773242460}, {"title": null, "start": 1773242460, "stop": 1773243000}, {"title": null, "start": 1773243000, "stop": 1773244800}, {"title": null, "start": 1773244800, "stop": 1773245760}, {"title": null, "start": 1773245760, "stop": 1773246600}, {"title": null, "start": 1773246600, "stop": 1773247560}, {"title": null, "start": 1773247560, "stop": 1773247860}, {"title": null, "start": 1773247860, "stop": 1773248400}, {"title": null, "start": 1773248400, "stop": 1773249120}, {"title": null, "start": 1773249120, "stop": 1773252000}, {"title": null, "start": 1773252000, "stop": 1773252960}, {"title": null, "start": 1773252960, "stop": 1773253260}, {"title": null, "start": 1773253260, "stop": 1773253800}, {"title": null, "start": 1773253800, "stop": 1773255600}, {"title": null, "start": 1773255600, "stop": 1773256500}, {"title": null, "start": 1773256500, "stop": 1773256800}, {"title": null, "start": 1773256800, "stop": 1773257400}, {"title": null, "start": 1773257400, "stop": 1773257760}, {"title": null, "start": 1773257760, "stop": 1773258240}, {"title": null, "start": 1773258240, "stop": 1773259200}, {"title": null, "start": 1773259200, "stop": 1773260100}, {"title": null, "start": 1773260100, "stop": 1773260400}, {"title": null, "start": 1773260400, "stop": 1773261000}, {"title": null, "start": 1773261000, "stop": 1773261840}, {"title": null, "start": 1773261840, "stop": 1773262800}, {"title": null, "start": 1773262800, "stop": 1773263700}, {"title": null, "start": 1773263700, "stop": 1773264600}, {"title": null, "start": 1773264600, "stop": 1773265140}, {"title": null, "start": 1773265140, "stop": 1773265380}, {"title": null, "start": 1773265380, "stop": 1773265740}, {"title": null, "start": 1773265740, "stop": 1773265860}, {"title": null, "start": 1773265860, "stop": 1773266400}, {"title": null, "start": 1773266400, "stop": 1773267300}, {"title": null, "start": 1773267300, "stop": 1773270000}, {"title": null, "start": 1773270000, "stop": 1773270900}, {"title": null, "start": 1773270900, "stop": 1773271800}, {"title": null, "start": 1773271800, "stop": 1773272700}, {"title": null, "start": 1773272700, "stop": 1773273600}, {"title": null, "start": 1773273600, "stop": 1773274500}, {"title": null, "start": 1773274500, "stop": 1773275400}, {"title": null, "start": 1773275400, "stop": 1773276300}, {"title": null, "start": 1773276300, "stop": 1773276660}, {"title": null, "start": 1773276660, "stop": 1773277200}, {"title": null, "start": 1773277200, "stop": 1773277860}, {"title": null, "start": 1773277860, "stop": 1773280500}, {"title": null, "start": 1773280500, "stop": 1773280800}, {"title": null, "start": 1773280800, "stop": 1773281400}, {"title": null, "start": 1773281400, "stop": 1773282600}, {"title": null, "start": 1773282600, "stop": 1773283200}, {"title": null, "start": 1773283200, "stop": 1773284400}, {"title": null, "start": 1773284400, "stop": 1773285300}, {"title": null, "start": 1773285300, "stop": 1773286200}, {"title": null, "start": 1773286200, "stop": 1773287100}, {"title": null, "start": 1773287100, "stop": 1773288000}, {"title": null, "start": 1773288000, "stop": 1773289320}, {"title": null, "start": 1773289320, "stop": 1773289800}, {"title": null, "start": 1773289800, "stop": 1773291060}, {"title": null, "start": 1773291060, "stop": 1773291600}, {"title": null, "start": 1773291600, "stop": 1773377460}, {"title": null, "start": 1773377460, "stop": 1773378000}, {"title": null, "start": 1773378000, "stop": 1773378960}, {"title": null, "start": 1773378960, "stop": 1773379260}, {"title": null, "start": 1773379260, "stop": 1773379800}, {"title": null, "start": 1773379800, "stop": 1773380760}, {"title": null, "start": 1773380760, "stop": 1773381060}, {"title": null, "start": 1773381060, "stop": 1773381600}, {"title": null, "start": 1773381600, "stop": 1773382500}, {"title": null, "start": 1773382500, "stop": 1773383400}, {"title": null, "start": 1773383400, "stop": 1773384360}, {"title": null, "start": 1773384360, "stop": 1773385200}, {"title": null, "start": 1773385200, "stop": 1773386520}, {"title": null, "start": 1773386520, "stop": 1773387000}, {"title": null, "start": 1773387000, "stop": 1773387720}, {"title": null, "start": 1773387720, "stop": 1773388020}, {"title": null, "start": 1773388020, "stop": 1773388320}, {"title": null, "start": 1773388320, "stop": 1773388800}, {"title": null, "start": 1773388800, "stop": 1773391500}, {"title": null, "start": 1773391500, "stop": 1773391800}, {"title": null, "start": 1773391800, "stop": 1773392400}, {"title": null, "start": 1773392400, "stop": 1773393000}, {"title": null, "start": 1773393000, "stop": 1773394200}, {"title": null, "start": 1773394200, "stop": 1773394800}, {"title": null, "start": 1773394800, "stop": 1773395520}, {"title": null, "start": 1773395520, "stop": 1773396000}, {"title": null, "start": 1773396000, "stop": 1773396900}, {"title": null, "start": 1773396900, "stop": 1773397800}, {"title": null, "start": 1773397800, "stop": 1773398700}, {"title": null, "start": 1773398700, "stop": 1773399000}, {"title": null, "start": 1773399000, "stop": 1773399600}, {"title": null, "start": 1773399600, "stop": 1773401400}, {"title": null, "start": 1773401400, "stop": 1773402840}]