[{"title": "Affari al buio", "start": 1772993100, "stop": 1772994300}, {"title": "Enigmi alieni", "start": 1772994300, "stop": 1772997600}, {"title": "Una storia pericolosa con...", "start": 1773000600, "stop": 1773003600}, {"title": "I mitici anni 90", "start": 1773003600, "stop": 1773006900}, {"title": "Disney - 100 anni di magia", "start": 1773006900, "stop": 1773009900}, {"title": "Il fuoco di spade", "start": 1773009900, "stop": 1773012900}, {"title": "Affari al buio", "start": 1773012900, "stop": 1773014400}, {"title": "Affari al buio", "start": 1773014400, "stop": 1773015900}, {"title": "Affari di famiglia", "start": 1773015900, "stop": 1773018900}, {"title": "Enigmi alieni", "start": 1773018900, "stop": 1773021600}, {"title": "Nazisti: I complici del Fuhrer", "start": 1773021600, "stop": 1773025200}, {"title": "Seconda Guerra a colori: la...", "start": 1773025200, "stop": 1773028500}, {"title": "Seconda Guerra a colori: la...", "start": 1773028500, "stop": 1773032400}, {"title": "Pillole di Storia", "start": 1773032400, "stop": 1773033600}, {"title": "Odissea: oltre il mito", "start": 1773033600, "stop": 1773036600}, {"title": "Ancient Powers", "start": 1773036600, "stop": 1773040200}, {"title": "Bermuda: i misteri degli abissi", "start": 1773040200, "stop": 1773042900}, {"title": "Seconda Guerra a colori: la...", "start": 1773042900, "stop": 1773046800}, {"title": "La Guerra Degli Italiani", "start": 1773046800, "stop": 1773050700}, {"title": "Grandi misteri della storia", "start": 1773050700, "stop": 1773053700}, {"title": "Affari al buio", "start": 1773053700, "stop": 1773055200}, {"title": "Affari al buio", "start": 1773055200, "stop": 1773056700}, {"title": "Affari di famiglia", "start": 1773056700, "stop": 1773060000}, {"title": "Enigmi alieni", "start": 1773060000, "stop": 1773063000}, {"title": "Macchine da guerra", "start": 1773063000, "stop": 1773066900}, {"title": "Grandi battaglie della...", "start": 1773066900, "stop": 1773070200}, {"title": "Seconda Guerra a colori: la...", "start": 1773070200, "stop": 1773073800}, {"title": "La Guerra Degli Italiani", "start": 1773073800, "stop": 1773077100}, {"title": "Affari al buio", "start": 1773077100, "stop": 1773078600}, {"title": "Affari al buio", "start": 1773078600, "stop": 1773080100}, {"title": "Enigmi alieni", "start": 1773080100, "stop": 1773083100}, {"title": "Affari di famiglia", "start": 1773083100, "stop": 1773086100}, {"title": "I seguaci del Fuhrer", "start": 1773086100, "stop": 1773090000}, {"title": "Nazisti: I complici del Fuhrer", "start": 1773090000, "stop": 1773093900}, {"title": "Il populista", "start": 1773093900, "stop": 1773097200}, {"title": "La Guerra Degli Italiani", "start": 1773097200, "stop": 1773100800}, {"title": "Affari al buio", "start": 1773100800, "stop": 1773102300}, {"title": "Affari al buio", "start": 1773102300, "stop": 1773103800}, {"title": "Affari di famiglia", "start": 1773103800, "stop": 1773106800}, {"title": "Enigmi alieni", "start": 1773106800, "stop": 1773109500}, {"title": "Nazisti: I complici del Fuhrer", "start": 1773109500, "stop": 1773112800}, {"title": "Affari al buio", "start": 1772993100, "stop": 1772994300}, {"title": "Enigmi alieni", "start": 1772994300, "stop": 1773000600}, {"title": "Una storia pericolosa con...", "start": 1773000600, "stop": 1773003600}, {"title": "I mitici anni 90", "start": 1773003600, "stop": 1773006900}, {"title": "Disney - 100 anni di magia", "start": 1773006900, "stop": 1773009900}, {"title": "Il fuoco di spade", "start": 1773009900, "stop": 1773012900}, {"title": "Affari al buio", "start": 1773012900, "stop": 1773014400}, {"title": "Affari al buio", "start": 1773014400, "stop": 1773015900}, {"title": "Affari di famiglia", "start": 1773015900, "stop": 1773018900}, {"title": "Enigmi alieni", "start": 1773018900, "stop": 1773021600}, {"title": "Nazisti: I complici del Fuhrer", "start": 1773021600, "stop": 1773025200}, {"title": "Seconda Guerra a colori: la...", "start": 1773025200, "stop": 1773028500}, {"title": "Seconda Guerra a colori: la...", "start": 1773028500, "stop": 1773032400}, {"title": "Pillole di Storia", "start": 1773032400, "stop": 1773033600}, {"title": "Odissea: oltre il mito - Stag. 1 Ep. 6 - Atto finale", "start": 1773033600, "stop": 1773036600}, {"title": "Ancient Powers", "start": 1773036600, "stop": 1773040200}, {"title": "Bermuda: i misteri degli abissi", "start": 1773040200, "stop": 1773042900}, {"title": "Seconda Guerra a colori: la...", "start": 1773042900, "stop": 1773046800}, {"title": "La Guerra Degli Italiani", "start": 1773046800, "stop": 1773050700}, {"title": "Grandi misteri della storia", "start": 1773050700, "stop": 1773053700}, {"title": "Affari al buio", "start": 1773053700, "stop": 1773055200}, {"title": "Affari al buio", "start": 1773055200, "stop": 1773056700}, {"title": "Affari di famiglia", "start": 1773056700, "stop": 1773060000}, {"title": "Enigmi alieni", "start": 1773060000, "stop": 1773063000}, {"title": "Macchine da guerra", "start": 1773063000, "stop": 1773066900}, {"title": "Grandi battaglie della...", "start": 1773066900, "stop": 1773070200}, {"title": "Seconda Guerra a colori: la...", "start": 1773070200, "stop": 1773073800}, {"title": "La Guerra Degli Italiani", "start": 1773073800, "stop": 1773077100}, {"title": "Affari al buio", "start": 1773077100, "stop": 1773078600}, {"title": "Affari al buio", "start": 1773078600, "stop": 1773080100}, {"title": "Enigmi alieni", "start": 1773080100, "stop": 1773083100}, {"title": "Affari di famiglia", "start": 1773083100, "stop": 1773086100}, {"title": "I seguaci del Fuhrer", "start": 1773086100, "stop": 1773090000}, {"title": "Nazisti: I complici del Fuhrer", "start": 1773090000, "stop": 1773093900}, {"title": "Il populista", "start": 1773093900, "stop": 1773097200}, {"title": "La Guerra Degli Italiani", "start": 1773097200, "stop": 1773100800}, {"title": "Affari al buio", "start": 1773100800, "stop": 1773102300}, {"title": "Affari al buio", "start": 1773102300, "stop": 1773103800}, {"title": "Affari di famiglia", "start": 1773103800, "stop": 1773106800}, {"title": "Enigmi alieni", "start": 1773106800, "stop": 1773109500}, {"title": "Nazisti: I complici del Fuhrer", "start": 1773109500, "stop": 1773112800}, {"title": "Grandi battaglie della...", "start": 1773112800, "stop": 1773115800}, {"title": "Seconda Guerra a colori: la...", "start": 1773115800, "stop": 1773118800}, {"title": "Pillole di Storia", "start": 1773118800, "stop": 1773120000}, {"title": "Il mito del cavallo di Troia", "start": 1773120000, "stop": 1773123600}, {"title": "Gli otto giorni che fecero Roma", "start": 1773123600, "stop": 1773126900}, {"title": "Bermuda: I misteri degli abissi", "start": 1773126900, "stop": 1773129900}, {"title": "Seconda Guerra a colori: la...", "start": 1773129900, "stop": 1773133500}, {"title": "La Guerra Degli Italiani", "start": 1773133500, "stop": 1773138000}, {"title": "Grandi misteri della storia", "start": 1773138000, "stop": 1773141000}, {"title": "Affari al buio", "start": 1773141000, "stop": 1773142500}, {"title": "Affari al buio", "start": 1773142500, "stop": 1773144000}, {"title": "Affari di famiglia", "start": 1773144000, "stop": 1773147300}, {"title": "Enigmi alieni", "start": 1773147300, "stop": 1773150300}, {"title": "Macchine da guerra", "start": 1773150300, "stop": 1773153900}, {"title": "Grandi battaglie della 2a...", "start": 1773153900, "stop": 1773157500}, {"title": "Seconda Guerra a colori: la...", "start": 1773157500, "stop": 1773160800}, {"title": "La Guerra Degli Italiani", "start": 1773160800, "stop": 1773164400}, {"title": "Affari al buio", "start": 1773164400, "stop": 1773165900}, {"title": "Affari al buio", "start": 1773165900, "stop": 1773167400}, {"title": "Enigmi alieni", "start": 1773167400, "stop": 1773170400}, {"title": "Affari di famiglia", "start": 1773170400, "stop": 1773173400}, {"title": "Il fuoco di spade", "start": 1773173400, "stop": 1773176400}]