[{"title": "RADIO2 HITS", "start": 1773000000, "stop": 1773003600}, {"title": "MUSICAL BOX", "start": 1773003600, "stop": 1773010800}, {"title": "RADIO2 HITS", "start": 1773010800, "stop": 1773028800}, {"title": "GOOD MORNING RADIO2", "start": 1773028800, "stop": 1773030600}, {"title": "GR 2", "start": 1773030600, "stop": 1773031020}, {"title": "segue GOOD MORNING RADIO2", "start": 1773031020, "stop": 1773097200}, {"title": "RADIO2 HITS", "start": 1773097200, "stop": 1773115200}, {"title": "GOOD MORNING RADIO2", "start": 1773115200, "stop": 1773117000}, {"title": "GR 2", "start": 1773117000, "stop": 1773117420}, {"title": "segue GOOD MORNING RADIO2", "start": 1773117420, "stop": 1773118800}, {"title": "LA SVEGLIANZA", "start": 1773118800, "stop": 1773120600}, {"title": "GR 2", "start": 1773120600, "stop": 1773121500}, {"title": "IL RUGGITO DEL CONIGLIO", "start": 1773121500, "stop": 1773124200}, {"title": "GR 2", "start": 1773124200, "stop": 1773124500}, {"title": "segue IL RUGGITO DEL CONIGLIO", "start": 1773124500, "stop": 1773131400}, {"title": "Maschio selvaggio", "start": 1773000000, "stop": 1773003600}, {"title": "Radio2 Hits", "start": 1773003600, "stop": 1773007200}, {"title": "Musical Box", "start": 1773007200, "stop": 1773032400}, {"title": "Good Morning Radio2", "start": 1773032400, "stop": 1773036000}, {"title": "La Pennicanza", "start": 1773036000, "stop": 1773037800}, {"title": "GR 2", "start": 1773037800, "stop": 1773038700}, {"title": "Il Ruggito del Coniglio", "start": 1773038700, "stop": 1773048600}, {"title": "GR 2", "start": 1773048600, "stop": 1773048900}, {"title": "Radio2 Social Club", "start": 1773048900, "stop": 1773054000}, {"title": "Radio2 stai Serena", "start": 1773054000, "stop": 1773059400}, {"title": "GR 2", "start": 1773059400, "stop": 1773060300}, {"title": "La Pennicanza", "start": 1773060300, "stop": 1773063000}, {"title": "Radio2 music room", "start": 1773063000, "stop": 1773068400}, {"title": "Lillo e Greg 610", "start": 1773068400, "stop": 1773070200}, {"title": "Il pomeriggio di Radio2", "start": 1773070200, "stop": 1773075600}, {"title": "Radio2 matti da legare", "start": 1773075600, "stop": 1773081000}, {"title": "GR 2", "start": 1773081000, "stop": 1773081900}, {"title": "Caterpillar", "start": 1773081900, "stop": 1773086400}, {"title": "Chiamami Radio2", "start": 1773086400, "stop": 1773090000}, {"title": "Radio2 alle dieci della sera - Sport & musica", "start": 1773090000, "stop": 1773093600}, {"title": "I Lunatici", "start": 1773093600, "stop": 1773106200}, {"title": "Radio2 matti da legare", "start": 1773106200, "stop": 1773111000}, {"title": "Radio2 Hits", "start": 1773111000, "stop": 1773118800}, {"title": "Good Morning Radio2", "start": 1773118800, "stop": 1773122400}, {"title": "La Pennicanza", "start": 1773122400, "stop": 1773124200}, {"title": "GR 2", "start": 1773124200, "stop": 1773125100}, {"title": "Il Ruggito del Coniglio", "start": 1773125100, "stop": 1773135000}, {"title": "GR 2", "start": 1773135000, "stop": 1773135300}, {"title": "Radio2 Social Club", "start": 1773135300, "stop": 1773140400}, {"title": "Radio2 stai Serena", "start": 1773140400, "stop": 1773145800}, {"title": "GR 2", "start": 1773145800, "stop": 1773146700}, {"title": "La Pennicanza", "start": 1773146700, "stop": 1773149400}, {"title": "Radio2 music room", "start": 1773149400, "stop": 1773154800}, {"title": "Lillo e Greg 610", "start": 1773154800, "stop": 1773156600}, {"title": "Il pomeriggio di Radio2", "start": 1773156600, "stop": 1773162000}, {"title": "Radio2 matti da legare", "start": 1773162000, "stop": 1773167400}, {"title": "GR 2", "start": 1773167400, "stop": 1773168300}, {"title": "Caterpillar", "start": 1773168300, "stop": 1773172800}, {"title": "Chiamami Radio2", "start": 1773172800, "stop": 1773176400}, {"title": "Radio2 alle dieci della sera - Sport & musica", "start": 1773176400, "stop": 1773180000}]