[{"title": null, "start": 1773369000, "stop": 1773370800}, {"title": null, "start": 1773370800, "stop": 1773378000}, {"title": null, "start": 1773378000, "stop": 1773385200}, {"title": null, "start": 1773385200, "stop": 1773386100}, {"title": null, "start": 1773386100, "stop": 1773393300}, {"title": null, "start": 1773393300, "stop": 1773400500}, {"title": null, "start": 1773400500, "stop": 1773406800}, {"title": null, "start": 1773406800, "stop": 1773410400}, {"title": null, "start": 1773410400, "stop": 1773416700}, {"title": null, "start": 1773416700, "stop": 1773423900}, {"title": null, "start": 1773423900, "stop": 1773424800}, {"title": null, "start": 1773424800, "stop": 1773426600}, {"title": null, "start": 1773426600, "stop": 1773428400}, {"title": null, "start": 1773428400, "stop": 1773431100}, {"title": null, "start": 1773431100, "stop": 1773438300}, {"title": null, "start": 1773438300, "stop": 1773442800}, {"title": null, "start": 1773442800, "stop": 1773444600}, {"title": null, "start": 1773444600, "stop": 1773446400}, {"title": null, "start": 1773446400, "stop": 1773448200}, {"title": null, "start": 1773448200, "stop": 1773455400}, {"title": null, "start": 1773455400, "stop": 1773457200}, {"title": null, "start": 1773457200, "stop": 1773464400}, {"title": null, "start": 1773464400, "stop": 1773470700}, {"title": null, "start": 1773470700, "stop": 1773472500}, {"title": null, "start": 1773472500, "stop": 1773474300}, {"title": null, "start": 1773474300, "stop": 1773481500}, {"title": null, "start": 1773481500, "stop": 1773483300}, {"title": null, "start": 1773483300, "stop": 1773489600}, {"title": null, "start": 1773489600, "stop": 1773491400}, {"title": null, "start": 1773491400, "stop": 1773497700}, {"title": null, "start": 1773497700, "stop": 1773498600}, {"title": null, "start": 1773498600, "stop": 1773505800}, {"title": null, "start": 1773505800, "stop": 1773507600}, {"title": null, "start": 1773507600, "stop": 1773508500}, {"title": null, "start": 1773508500, "stop": 1773509400}, {"title": null, "start": 1773509400, "stop": 1773516600}, {"title": null, "start": 1773516600, "stop": 1773517500}, {"title": null, "start": 1773517500, "stop": 1773524700}, {"title": null, "start": 1773524700, "stop": 1773529200}, {"title": null, "start": 1773529200, "stop": 1773530100}, {"title": null, "start": 1773530100, "stop": 1773531000}, {"title": null, "start": 1773531000, "stop": 1773532800}, {"title": null, "start": 1773532800, "stop": 1773534600}, {"title": null, "start": 1773534600, "stop": 1773541800}, {"title": null, "start": 1773541800, "stop": 1773543600}, {"title": null, "start": 1773543600, "stop": 1773544500}, {"title": null, "start": 1773544500, "stop": 1773550800}]