[{"title": null, "start": 1773107700, "stop": 1773114000}, {"title": null, "start": 1773114000, "stop": 1773123000}, {"title": null, "start": 1773123000, "stop": 1773128400}, {"title": null, "start": 1773128400, "stop": 1773135000}, {"title": null, "start": 1773135000, "stop": 1773142500}, {"title": null, "start": 1773142500, "stop": 1773150300}, {"title": null, "start": 1773150300, "stop": 1773157800}, {"title": null, "start": 1773157800, "stop": 1773165900}, {"title": null, "start": 1773165900, "stop": 1773172800}, {"title": null, "start": 1773172800, "stop": 1773181800}, {"title": null, "start": 1773181800, "stop": 1773188400}, {"title": null, "start": 1773188400, "stop": 1773193200}, {"title": null, "start": 1773193200, "stop": 1773194400}, {"title": null, "start": 1773194400, "stop": 1773201900}, {"title": null, "start": 1773201900, "stop": 1773208500}, {"title": null, "start": 1773208500, "stop": 1773213900}, {"title": null, "start": 1773213900, "stop": 1773221400}, {"title": null, "start": 1773221400, "stop": 1773227400}, {"title": null, "start": 1773227400, "stop": 1773234000}, {"title": null, "start": 1773234000, "stop": 1773240900}, {"title": null, "start": 1773240900, "stop": 1773246300}, {"title": null, "start": 1773246300, "stop": 1773253200}, {"title": null, "start": 1773253200, "stop": 1773259200}, {"title": null, "start": 1773259200, "stop": 1773266400}, {"title": null, "start": 1773266400, "stop": 1773275400}, {"title": null, "start": 1773275400, "stop": 1773283200}, {"title": null, "start": 1773283200, "stop": 1773284100}, {"title": null, "start": 1773284100, "stop": 1773291900}]