[{"title": null, "start": 1773364200, "stop": 1773372000}, {"title": null, "start": 1773372000, "stop": 1773378600}, {"title": null, "start": 1773378600, "stop": 1773385800}, {"title": null, "start": 1773385800, "stop": 1773394500}, {"title": null, "start": 1773394500, "stop": 1773401100}, {"title": null, "start": 1773401100, "stop": 1773407100}, {"title": null, "start": 1773407100, "stop": 1773413100}, {"title": null, "start": 1773413100, "stop": 1773418800}, {"title": null, "start": 1773418800, "stop": 1773424800}, {"title": null, "start": 1773424800, "stop": 1773432000}, {"title": null, "start": 1773432000, "stop": 1773440100}, {"title": null, "start": 1773440100, "stop": 1773447600}, {"title": null, "start": 1773447600, "stop": 1773455100}, {"title": null, "start": 1773455100, "stop": 1773460800}, {"title": null, "start": 1773460800, "stop": 1773468000}, {"title": null, "start": 1773468000, "stop": 1773474300}, {"title": null, "start": 1773474300, "stop": 1773480900}, {"title": null, "start": 1773480900, "stop": 1773487500}, {"title": null, "start": 1773487500, "stop": 1773496200}, {"title": null, "start": 1773496200, "stop": 1773502500}, {"title": null, "start": 1773502500, "stop": 1773510600}, {"title": null, "start": 1773510600, "stop": 1773518400}, {"title": null, "start": 1773518400, "stop": 1773525900}, {"title": null, "start": 1773525900, "stop": 1773532200}, {"title": null, "start": 1773532200, "stop": 1773540600}, {"title": null, "start": 1773540600, "stop": 1773548100}, {"title": null, "start": 1773548100, "stop": 1773555000}]