[{"title": "Il cacciatore di giganti", "start": 1772987100, "stop": 1772994000}, {"title": "Dragon Trainer", "start": 1772994000, "stop": 1773000000}, {"title": "Una notte al museo", "start": 1773000000, "stop": 1773006900}, {"title": "Il giorno piu bello del mondo", "start": 1773006900, "stop": 1773013200}, {"title": "Balto e Togo - La leggenda", "start": 1773013200, "stop": 1773018300}, {"title": "Alla fine ci sei tu", "start": 1773018300, "stop": 1773024000}, {"title": "La Famiglia Addams", "start": 1773024000, "stop": 1773030000}, {"title": "Ops! È già Natale", "start": 1773030000, "stop": 1773035700}, {"title": "Dolcissime", "start": 1773035700, "stop": 1773041100}, {"title": "The Portable Door", "start": 1773041100, "stop": 1773048300}, {"title": "Dragon Trainer", "start": 1773048300, "stop": 1773054300}, {"title": "Una notte al museo", "start": 1773054300, "stop": 1773060900}, {"title": "La Famiglia Addams", "start": 1773060900, "stop": 1773066900}, {"title": "Il giorno piu bello del mondo", "start": 1773066900, "stop": 1773073200}, {"title": "Ritorno al futuro - Parte II", "start": 1773073200, "stop": 1773080100}, {"title": "Dragon Trainer 2", "start": 1773080100, "stop": 1773086400}, {"title": "10 giorni senza mamma", "start": 1773086400, "stop": 1773092100}, {"title": "Il lupo e il leone", "start": 1773092100, "stop": 1773098400}, {"title": "Questo o quello - Speciale", "start": 1773098400, "stop": 1773099300}, {"title": "The Portable Door", "start": 1773099300, "stop": 1773106200}, {"title": "Il prodigioso Maurice", "start": 1773106200, "stop": 1773111600}, {"title": "Cè tempo", "start": 1773111600, "stop": 1773117900}, {"title": "Il cacciatore di giganti", "start": 1772987100, "stop": 1772994000}, {"title": "Dragon Trainer", "start": 1772994000, "stop": 1773000000}, {"title": "Una notte al museo", "start": 1773000000, "stop": 1773006900}, {"title": "Il giorno piu bello del mondo", "start": 1773006900, "stop": 1773013200}, {"title": "Balto e Togo - La leggenda", "start": 1773013200, "stop": 1773018300}, {"title": "Alla fine ci sei tu", "start": 1773018300, "stop": 1773024000}, {"title": "La Famiglia Addams", "start": 1773024000, "stop": 1773030000}, {"title": "Ops! È già Natale", "start": 1773030000, "stop": 1773035700}, {"title": "Dolcissime", "start": 1773035700, "stop": 1773041100}, {"title": "The Portable Door", "start": 1773041100, "stop": 1773048300}, {"title": "Dragon Trainer", "start": 1773048300, "stop": 1773054300}, {"title": "Una notte al museo", "start": 1773054300, "stop": 1773060900}, {"title": "La Famiglia Addams", "start": 1773060900, "stop": 1773066900}, {"title": "Il giorno piu bello del mondo", "start": 1773066900, "stop": 1773073200}, {"title": "Ritorno al futuro - Parte II", "start": 1773073200, "stop": 1773080100}, {"title": "Dragon Trainer 2", "start": 1773080100, "stop": 1773086400}, {"title": "10 giorni senza mamma", "start": 1773086400, "stop": 1773092100}, {"title": "Il lupo e il leone", "start": 1773092100, "stop": 1773098400}, {"title": "Questo o quello - Men in Black", "start": 1773098400, "stop": 1773099300}, {"title": "The Portable Door", "start": 1773099300, "stop": 1773106200}, {"title": "Il prodigioso Maurice", "start": 1773106200, "stop": 1773111600}]