[{"title": null, "start": 1773281100, "stop": 1773284400}, {"title": null, "start": 1773284400, "stop": 1773291000}, {"title": null, "start": 1773294300, "stop": 1773295200}, {"title": null, "start": 1773302100, "stop": 1773304800}, {"title": null, "start": 1773304800, "stop": 1773307500}, {"title": null, "start": 1773307500, "stop": 1773310200}, {"title": null, "start": 1773310200, "stop": 1773314100}, {"title": null, "start": 1773314100, "stop": 1773317100}, {"title": null, "start": 1773317100, "stop": 1773323100}, {"title": null, "start": 1773323100, "stop": 1773326700}, {"title": null, "start": 1773326700, "stop": 1773330600}, {"title": null, "start": 1773330600, "stop": 1773333600}, {"title": null, "start": 1773333600, "stop": 1773336900}, {"title": null, "start": 1773336900, "stop": 1773342300}, {"title": null, "start": 1773342300, "stop": 1773348000}, {"title": null, "start": 1773348000, "stop": 1773351000}, {"title": null, "start": 1773351000, "stop": 1773353700}, {"title": null, "start": 1773360900, "stop": 1773363900}, {"title": null, "start": 1773363900, "stop": 1773366000}, {"title": null, "start": 1773366000, "stop": 1773369000}, {"title": null, "start": 1773369000, "stop": 1773372000}]